{
  "categories": [
    {
      "name": "New Releases",
      "items": [
        {
          "id": "nr1",
          "name": "Oppenheimer",
          "description": "The story of American scientist J. Robert Oppenheimer and his role in the development of the atomic bomb.",
          "thumbnail": "https://m.media-amazon.com/images/M/MV5BMDBmYTZjNjUtN2M1MS00MTQ2LTk2ODgtNzc2M2QyZGE5NTVjXkEyXkFqcGdeQXVyNzAwMjU2MTY@._V1_.jpg",
          "videoUrl": "https://www.youtube.com/watch?v=uYPbbksJxIg",
          "releaseDate": "2023",
          "duration": "3h 0m",
          "episodes": [
            {
              "id": "nr1_ep1",
              "name": "The Beginning",
              "thumbnail": "https://m.media-amazon.com/images/M/MV5BMDBmYTZjNjUtN2M1MS00MTQ2LTk2ODgtNzc2M2QyZGE5NTVjXkEyXkFqcGdeQXVyNzAwMjU2MTY@._V1_.jpg",
              "videoUrl": "https://www.youtube.com/watch?v=uYPbbksJxIg",
              "duration": "1h 0m",
              "episodeNumber": 1
            },
            {
              "id": "nr1_ep2",
              "name": "The Development",
              "thumbnail": "https://m.media-amazon.com/images/M/MV5BMDBmYTZjNjUtN2M1MS00MTQ2LTk2ODgtNzc2M2QyZGE5NTVjXkEyXkFqcGdeQXVyNzAwMjU2MTY@._V1_.jpg",
              "videoUrl": "https://www.youtube.com/watch?v=uYPbbksJxIg",
              "duration": "1h 0m",
              "episodeNumber": 2
            },
            {
              "id": "nr1_ep3",
              "name": "The Conclusion",
              "thumbnail": "https://m.media-amazon.com/images/M/MV5BMDBmYTZjNjUtN2M1MS00MTQ2LTk2ODgtNzc2M2QyZGE5NTVjXkEyXkFqcGdeQXVyNzAwMjU2MTY@._V1_.jpg",
              "videoUrl": "https://www.youtube.com/watch?v=uYPbbksJxIg",
              "duration": "1h 0m",
              "episodeNumber": 3
            }
          ]
        },
        {
          "id": "nr2",
          "name": "Barbie",
          "description": "Barbie suffers a crisis that leads her to question her world and her existence.",
          "thumbnail": "https://m.media-amazon.com/images/M/MV5BNjU3N2QxNzYtMjk1NC00MTc4LTk1NTQtMmUxNTljM2I0NDA5XkEyXkFqcGdeQXVyODE5NzE3OTE@._V1_.jpg",
          "videoUrl": "https://www.youtube.com/watch?v=pBk4NYhWNMM",
          "releaseDate": "2023",
          "duration": "1h 54m",
          "episodes": [
            {
              "id": "nr2_ep1",
              "name": "The Perfect Life",
              "thumbnail": "https://m.media-amazon.com/images/M/MV5BNjU3N2QxNzYtMjk1NC00MTc4LTk1NTQtMmUxNTljM2I0NDA5XkEyXkFqcGdeQXVyODE5NzE3OTE@._V1_.jpg",
              "videoUrl": "https://www.youtube.com/watch?v=pBk4NYhWNMM",
              "duration": "45m",
              "episodeNumber": 1
            },
            {
              "id": "nr2_ep2",
              "name": "The Real World",
              "thumbnail": "https://m.media-amazon.com/images/M/MV5BNjU3N2QxNzYtMjk1NC00MTc4LTk1NTQtMmUxNTljM2I0NDA5XkEyXkFqcGdeQXVyODE5NzE3OTE@._V1_.jpg",
              "videoUrl": "https://www.youtube.com/watch?v=pBk4NYhWNMM",
              "duration": "35m",
              "episodeNumber": 2
            },
            {
              "id": "nr2_ep3",
              "name": "The Discovery",
              "thumbnail": "https://m.media-amazon.com/images/M/MV5BNjU3N2QxNzYtMjk1NC00MTc4LTk1NTQtMmUxNTljM2I0NDA5XkEyXkFqcGdeQXVyODE5NzE3OTE@._V1_.jpg",
              "videoUrl": "https://www.youtube.com/watch?v=pBk4NYhWNMM",
              "duration": "34m",
              "episodeNumber": 3
            }
          ]
        }
      ]
    },
    {
      "name": "Action",
      "items": [
        {
          "id": "ac1",
          "name": "Mission: Impossible - Dead Reckoning",
          "description": "Ethan Hunt and his IMF team must track down a dangerous weapon before it falls into the wrong hands.",
          "thumbnail": "https://m.media-amazon.com/images/M/MV5BYzFiZjc1YzctMDY3Zi00NGE5LTlmNWEtN2Q3OWFjYjY1NGM2XkEyXkFqcGdeQXVyMTUyMTUzNjQ0._V1_.jpg",
          "videoUrl": "https://www.youtube.com/watch?v=avz06PDqDbM",
          "releaseDate": "2023",
          "duration": "2h 43m",
          "episodes": [
            {
              "id": "ac1_ep1",
              "name": "The Hunt Begins",
              "thumbnail": "https://m.media-amazon.com/images/M/MV5BYzFiZjc1YzctMDY3Zi00NGE5LTlmNWEtN2Q3OWFjYjY1NGM2XkEyXkFqcGdeQXVyMTUyMTUzNjQ0._V1_.jpg",
              "videoUrl": "https://www.youtube.com/watch?v=avz06PDqDbM",
              "duration": "55m",
              "episodeNumber": 1
            },
            {
              "id": "ac1_ep2",
              "name": "The Chase",
              "thumbnail": "https://m.media-amazon.com/images/M/MV5BYzFiZjc1YzctMDY3Zi00NGE5LTlmNWEtN2Q3OWFjYjY1NGM2XkEyXkFqcGdeQXVyMTUyMTUzNjQ0._V1_.jpg",
              "videoUrl": "https://www.youtube.com/watch?v=avz06PDqDbM",
              "duration": "54m",
              "episodeNumber": 2
            },
            {
              "id": "ac1_ep3",
              "name": "The Confrontation",
              "thumbnail": "https://m.media-amazon.com/images/M/MV5BYzFiZjc1YzctMDY3Zi00NGE5LTlmNWEtN2Q3OWFjYjY1NGM2XkEyXkFqcGdeQXVyMTUyMTUzNjQ0._V1_.jpg",
              "videoUrl": "https://www.youtube.com/watch?v=avz06PDqDbM",
              "duration": "54m",
              "episodeNumber": 3
            }
          ]
        },
        {
          "id": "ac2",
          "name": "John Wick: Chapter 4",
          "description": "John Wick uncovers a path to defeating The High Table.",
          "thumbnail": "https://m.media-amazon.com/images/M/MV5BMDExZGMyOTMtMDgyYi00NGIwLWJhMTEtOTdkZGFjNmZiMTEwXkEyXkFqcGdeQXVyMjM4NTM5NDY@._V1_.jpg",
          "videoUrl": "https://www.youtube.com/watch?v=qEVUtrk8_B4",
          "releaseDate": "2023",
          "duration": "2h 49m",
          "episodes": [
            {
              "id": "ac2_ep1",
              "name": "The Challenge",
              "thumbnail": "https://m.media-amazon.com/images/M/MV5BMDExZGMyOTMtMDgyYi00NGIwLWJhMTEtOTdkZGFjNmZiMTEwXkEyXkFqcGdeQXVyMjM4NTM5NDY@._V1_.jpg",
              "videoUrl": "https://www.youtube.com/watch?v=qEVUtrk8_B4",
              "duration": "56m",
              "episodeNumber": 1
            },
            {
              "id": "ac2_ep2",
              "name": "The Journey",
              "thumbnail": "https://m.media-amazon.com/images/M/MV5BMDExZGMyOTMtMDgyYi00NGIwLWJhMTEtOTdkZGFjNmZiMTEwXkEyXkFqcGdeQXVyMjM4NTM5NDY@._V1_.jpg",
              "videoUrl": "https://www.youtube.com/watch?v=qEVUtrk8_B4",
              "duration": "57m",
              "episodeNumber": 2
            },
            {
              "id": "ac2_ep3",
              "name": "The Final Duel",
              "thumbnail": "https://m.media-amazon.com/images/M/MV5BMDExZGMyOTMtMDgyYi00NGIwLWJhMTEtOTdkZGFjNmZiMTEwXkEyXkFqcGdeQXVyMjM4NTM5NDY@._V1_.jpg",
              "videoUrl": "https://www.youtube.com/watch?v=qEVUtrk8_B4",
              "duration": "56m",
              "episodeNumber": 3
            }
          ]
        }
      ]
    },
    {
      "name": "Sci-Fi",
      "items": [
        {
          "id": "sf1",
          "name": "Dune",
          "description": "A noble family becomes embroiled in a war for control over the galaxy's most valuable asset.",
          "thumbnail": "https://m.media-amazon.com/images/M/MV5BN2FjNmEyNWMtYzM0ZS00NjIyLTg5YzYtYThlMGVjNzE1OGViXkEyXkFqcGdeQXVyMTkxNjUyNQ@@._V1_.jpg",
          "videoUrl": "https://www.youtube.com/watch?v=8g18jFHCLXk",
          "releaseDate": "2021",
          "duration": "2h 35m",
          "episodes": [
            {
              "id": "sf1_ep1",
              "name": "House Atreides",
              "thumbnail": "https://m.media-amazon.com/images/M/MV5BN2FjNmEyNWMtYzM0ZS00NjIyLTg5YzYtYThlMGVjNzE1OGViXkEyXkFqcGdeQXVyMTkxNjUyNQ@@._V1_.jpg",
              "videoUrl": "https://www.youtube.com/watch?v=8g18jFHCLXk",
              "duration": "52m",
              "episodeNumber": 1
            },
            {
              "id": "sf1_ep2",
              "name": "The Spice",
              "thumbnail": "https://m.media-amazon.com/images/M/MV5BN2FjNmEyNWMtYzM0ZS00NjIyLTg5YzYtYThlMGVjNzE1OGViXkEyXkFqcGdeQXVyMTkxNjUyNQ@@._V1_.jpg",
              "videoUrl": "https://www.youtube.com/watch?v=8g18jFHCLXk",
              "duration": "51m",
              "episodeNumber": 2
            },
            {
              "id": "sf1_ep3",
              "name": "The Desert",
              "thumbnail": "https://m.media-amazon.com/images/M/MV5BN2FjNmEyNWMtYzM0ZS00NjIyLTg5YzYtYThlMGVjNzE1OGViXkEyXkFqcGdeQXVyMTkxNjUyNQ@@._V1_.jpg",
              "videoUrl": "https://www.youtube.com/watch?v=8g18jFHCLXk",
              "duration": "52m",
              "episodeNumber": 3
            }
          ]
        },
        {
          "id": "sf2",
          "name": "Blade Runner 2049",
          "description": "A young blade runner's discovery of a long-buried secret leads him to track down former blade runner Rick Deckard.",
          "thumbnail": "https://m.media-amazon.com/images/M/MV5BNzA1Njg4NzYxOV5BMl5BanBnXkFtZTgwODk5NjU3MzI@._V1_.jpg",
          "videoUrl": "https://www.youtube.com/watch?v=gCcx85zbxz4",
          "releaseDate": "2017",
          "duration": "2h 44m",
          "episodes": [
            {
              "id": "sf2_ep1",
              "name": "The Investigation",
              "thumbnail": "https://m.media-amazon.com/images/M/MV5BNzA1Njg4NzYxOV5BMl5BanBnXkFtZTgwODk5NjU3MzI@._V1_.jpg",
              "videoUrl": "https://www.youtube.com/watch?v=gCcx85zbxz4",
              "duration": "54m",
              "episodeNumber": 1
            },
            {
              "id": "sf2_ep2",
              "name": "The Secret",
              "thumbnail": "https://m.media-amazon.com/images/M/MV5BNzA1Njg4NzYxOV5BMl5BanBnXkFtZTgwODk5NjU3MzI@._V1_.jpg",
              "videoUrl": "https://www.youtube.com/watch?v=gCcx85zbxz4",
              "duration": "55m",
              "episodeNumber": 2
            },
            {
              "id": "sf2_ep3",
              "name": "The Truth",
              "thumbnail": "https://m.media-amazon.com/images/M/MV5BNzA1Njg4NzYxOV5BMl5BanBnXkFtZTgwODk5NjU3MzI@._V1_.jpg",
              "videoUrl": "https://www.youtube.com/watch?v=gCcx85zbxz4",
              "duration": "55m",
              "episodeNumber": 3
            }
          ]
        }
      ]
    },
    {
      "name": "Drama",
      "items": [
        {
          "id": "dr1",
          "name": "The Whale",
          "description": "A reclusive English teacher attempts to reconnect with his estranged teenage daughter.",
          "thumbnail": "https://m.media-amazon.com/images/M/MV5BZDQ4Njg4YTctNGZkYi00NWU1LWI4OTYtNmNjOWMyMjI1NWYzXkEyXkFqcGdeQXVyMTA3MDk2NDg2._V1_.jpg",
          "videoUrl": "https://www.youtube.com/watch?v=6VEGzCLPJsk",
          "releaseDate": "2022",
          "duration": "1h 57m",
          "episodes": [
            {
              "id": "dr1_ep1",
              "name": "The Teacher",
              "thumbnail": "https://m.media-amazon.com/images/M/MV5BZDQ4Njg4YTctNGZkYi00NWU1LWI4OTYtNmNjOWMyMjI1NWYzXkEyXkFqcGdeQXVyMTA3MDk2NDg2._V1_.jpg",
              "videoUrl": "https://www.youtube.com/watch?v=6VEGzCLPJsk",
              "duration": "39m",
              "episodeNumber": 1
            },
            {
              "id": "dr1_ep2",
              "name": "The Daughter",
              "thumbnail": "https://m.media-amazon.com/images/M/MV5BZDQ4Njg4YTctNGZkYi00NWU1LWI4OTYtNmNjOWMyMjI1NWYzXkEyXkFqcGdeQXVyMTA3MDk2NDg2._V1_.jpg",
              "videoUrl": "https://www.youtube.com/watch?v=6VEGzCLPJsk",
              "duration": "39m",
              "episodeNumber": 2
            },
            {
              "id": "dr1_ep3",
              "name": "The Reconciliation",
              "thumbnail": "https://m.media-amazon.com/images/M/MV5BZDQ4Njg4YTctNGZkYi00NWU1LWI4OTYtNmNjOWMyMjI1NWYzXkEyXkFqcGdeQXVyMTA3MDk2NDg2._V1_.jpg",
              "videoUrl": "https://www.youtube.com/watch?v=6VEGzCLPJsk",
              "duration": "39m",
              "episodeNumber": 3
            }
          ]
        },
        {
          "id": "dr2",
          "name": "Everything Everywhere All at Once",
          "description": "An aging Chinese immigrant is swept up in an insane adventure.",
          "thumbnail": "https://m.media-amazon.com/images/M/MV5BYTdiOTIyZTQtNmQ1OS00NjZlLWIyMTgtYzk5Y2M3ZDVmMDk1XkEyXkFqcGdeQXVyMTAzMDg4NzU0._V1_.jpg",
          "videoUrl": "https://www.youtube.com/watch?v=wxN1T1uxQ2g",
          "releaseDate": "2022",
          "duration": "2h 19m",
          "episodes": [
            {
              "id": "dr2_ep1",
              "name": "The Laundromat",
              "thumbnail": "https://m.media-amazon.com/images/M/MV5BYTdiOTIyZTQtNmQ1OS00NjZlLWIyMTgtYzk5Y2M3ZDVmMDk1XkEyXkFqcGdeQXVyMTAzMDg4NzU0._V1_.jpg",
              "videoUrl": "https://www.youtube.com/watch?v=wxN1T1uxQ2g",
              "duration": "46m",
              "episodeNumber": 1
            },
            {
              "id": "dr2_ep2",
              "name": "The Multiverse",
              "thumbnail": "https://m.media-amazon.com/images/M/MV5BYTdiOTIyZTQtNmQ1OS00NjZlLWIyMTgtYzk5Y2M3ZDVmMDk1XkEyXkFqcGdeQXVyMTAzMDg4NzU0._V1_.jpg",
              "videoUrl": "https://www.youtube.com/watch?v=wxN1T1uxQ2g",
              "duration": "47m",
              "episodeNumber": 2
            },
            {
              "id": "dr2_ep3",
              "name": "Everything, Everywhere",
              "thumbnail": "https://m.media-amazon.com/images/M/MV5BYTdiOTIyZTQtNmQ1OS00NjZlLWIyMTgtYzk5Y2M3ZDVmMDk1XkEyXkFqcGdeQXVyMTAzMDg4NzU0._V1_.jpg",
              "videoUrl": "https://www.youtube.com/watch?v=wxN1T1uxQ2g",
              "duration": "46m",
              "episodeNumber": 3
            }
          ]
        }
      ]
    }
  ]
}